setup.py
SquareMap.egg-info/PKG-INFO
SquareMap.egg-info/SOURCES.txt
SquareMap.egg-info/dependency_links.txt
SquareMap.egg-info/not-zip-safe
SquareMap.egg-info/requires.txt
SquareMap.egg-info/top_level.txt
squaremap/__init__.py
squaremap/squaremap.py