Metadata-Version: 1.1
Name: SquareMap
Version: 1.0.5
Summary: Hierarchic data-visualisation control for wxPython
Home-page: https://launchpad.net/squaremap
Author: Mike C. Fletcher
Author-email: mcfletch@vrplumber.com
License: BSD
Keywords: wxPython,squaremap
Platform: Any
Classifier: License :: OSI Approved :: BSD License
Classifier: Programming Language :: Python :: 2
Classifier: Programming Language :: Python :: 3
Classifier: Topic :: Software Development :: Libraries :: Python Modules
Classifier: Intended Audience :: Developers
